kitefoil/__init__.py
kitefoil/kitefoil.py
kitefoil-0.0.3.dist-info/LICENSE
kitefoil-0.0.3.dist-info/METADATA
kitefoil-0.0.3.dist-info/WHEEL
kitefoil-0.0.3.dist-info/top_level.txt
kitefoil-0.0.3.dist-info/RECORD
